SivantClass/__init__.py
SivantClass/sivant.py
SivantClass-0.0.2.dist-info/LICENSE.txt
SivantClass-0.0.2.dist-info/METADATA
SivantClass-0.0.2.dist-info/WHEEL
SivantClass-0.0.2.dist-info/top_level.txt
SivantClass-0.0.2.dist-info/RECORD
