Metadata-Version: 2.1
Name: SivantClass
Version: 0.0.2
Summary: A Python package to get weather reports for any location.
Home-page: https://github.com/sivant1361/sivant_hello
Author: Sivant M
Author-email: sivant1313@gmail.com
License: UNKNOWN
Platform: UNKNOWN
Classifier: License :: OSI Approved :: MIT License
Classifier: Programming Language :: Python :: 3
Classifier: Programming Language :: Python :: 3.7
